{
  "kind": "collectionType",
  "collectionName": "career_types",
  "info": {
    "singularName": "career-type",
    "pluralName": "career-types",
    "displayName": "Career Type",
    "description": ""
  },
  "options": {
    "draftAndPublish": true
  },
  "pluginOptions": {
    "i18n": {
      "localized": true
    }
  },
  "attributes": {
    "description": {
      "type": "string",
      "required": true,
      "pluginOptions": {
        "i18n": {
          "localized": true
        }
      }
    }
  }
}
